py3stun/__init__.py
py3stun/cli.py
py3stun/pystun.py
py3stun-0.1.1.dist-info/LICENSE
py3stun-0.1.1.dist-info/METADATA
py3stun-0.1.1.dist-info/WHEEL
py3stun-0.1.1.dist-info/entry_points.txt
py3stun-0.1.1.dist-info/top_level.txt
py3stun-0.1.1.dist-info/RECORD
