Metadata-Version: 2.1
Name: py3stun
Version: 0.1.1
Summary: A Python STUN client for getting NAT type and external IP (RFC 3489)
Author-email: "Nemo Xiong (original author: Justin Riley and gaohawk)" <xiongnemo@126.com>
Project-URL: Homepage, https://github.com/xiongnemo/py3stun
Project-URL: Bug Tracker, https://github.com/xiongnemo/py3stun/issues
Classifier: Programming Language :: Python :: 3
Classifier: License :: OSI Approved :: MIT License
Classifier: Operating System :: OS Independent
Classifier: Development Status :: 4 - Beta
Classifier: Topic :: Internet
Classifier: Topic :: System :: Networking :: Firewalls
Requires-Python: >=3.6
License-File: LICENSE
